vectorized2d/__init__.py
vectorized2d/array2d.py
vectorized2d/coordinate.py
vectorized2d/point2d.py
vectorized2d/vector2d.py
vectorized2d/utils/__init__.py
vectorized2d/utils/units.py
vectorized2d-0.0.7.dist-info/LICENSE
vectorized2d-0.0.7.dist-info/METADATA
vectorized2d-0.0.7.dist-info/WHEEL
vectorized2d-0.0.7.dist-info/top_level.txt
vectorized2d-0.0.7.dist-info/RECORD
