Metadata-Version: 2.1
Name: vectorized2d
Version: 0.0.7
Summary: This is a user-friendly wrapper to numpy arrays,    with batteries included and numba-enhanced performance.
Home-page: https://github.com/mishana/vectorized2d
Author: Michael Leybovich
Author-email: mishana4life@gmail.com
License: MIT
Platform: UNKNOWN
Classifier: License :: OSI Approved :: MIT License
Classifier: Programming Language :: Python :: 3
Classifier: Programming Language :: Python :: 3.8
Requires-Dist: numpy
Requires-Dist: fast-enum
Requires-Dist: numba
